{"assets/images/airship.png":["assets/images/airship.png"],"assets/images/airship_shiven.png":["assets/images/airship_shiven.png"],"assets/images/background.png":["assets/images/background.png"],"assets/images/cloud_lonely.png":["assets/images/cloud_lonely.png"],"assets/images/clouds_bg.png":["assets/images/clouds_bg.png"],"assets/images/clouds_mg_1.png":["assets/images/clouds_mg_1.png"],"assets/images/clouds_mg_1_lightened.png":["assets/images/clouds_mg_1_lightened.png"],"assets/images/clouds_mg_2.png":["assets/images/clouds_mg_2.png"],"assets/images/clouds_mg_3.png":["assets/images/clouds_mg_3.png"],"assets/images/crow350x400.png":["assets/images/crow350x400.png"],"assets/images/crow350x400_ishank.png":["assets/images/crow350x400_ishank.png"],"assets/images/glacial_mountains.png":["assets/images/glacial_mountains.png"],"assets/images/glacial_mountains_lightened.png":["assets/images/glacial_mountains_lightened.png"],"assets/images/sky.png":["assets/images/sky.png"],"assets/images/sky_lightened.png":["assets/images/sky_lightened.png"],"packages/cupertino_icons/assets/CupertinoIcons.ttf":["packages/cupertino_icons/assets/CupertinoIcons.ttf"]}